[
  {
    "id": "599308",
    "title": "Kuro Gal Kyonyuu Gimai wa Boku o Yasashiku Sakusei Shitai",
    "tags": [],
    "pages": null,
    "thumbnail_url": null
  },
  {
    "id": "599299",
    "title": "[Natsuzo] The Reluctant Sister Who Wants to Focus On Study Can't Resist Temptation From the Brother She Shares Perfect Body Compatibility With",
    "tags": [],
    "pages": null,
    "thumbnail_url": null
  },
  {
    "id": "599296",
    "title": "[Poriuretan] Niizuma no Koharu, Netorase ︱ Newlywed Koharu, Netorase [English] [keyfew] [Digital]",
    "tags": [],
    "pages": null,
    "thumbnail_url": null
  },
  {
    "id": "599165",
    "title": "[Genkai Hatsudensho] Onna Gyaru Joushi to Furin Suru Hanashi 3 | Having an Affair with My Blonde Bombshell Boss – Part 3 [English] [Castle TL]",
    "tags": [],
    "pages": null,
    "thumbnail_url": null
  },
  {
    "id": "599149",
    "title": "[POTATO BOMB (ONEDOO)] Gohoushi Itashimasu Rental Maid! | At Your Service: Rental Maid! [English] [Digital]",
    "tags": [],
    "pages": null,
    "thumbnail_url": null
  }
]